{
  "name": "",
  "menuBackgroundImage": "",
  "defaultRessources": {
    "backgrounds": [
      "https://tari101190.github.io/Cartomancer.github.io/Cartomancer%20Playsheet.jpg"
    ],
    "decksUrl": "https://tari101190.github.io/Cartomancer.github.io/CartomancerDecks.json"
  },
  "customHelp": "",
  "cardRotation": "90",
  "cards": {
    "dataUrl": "https://tari101190.github.io/Cartomancer.github.io/CartomancerCardList.json",
    "cardBack": "https://tari101190.github.io/Cartomancer.github.io/Cartomancer-089.jpg"
  },
  "deckBuilding": {
    "mainFilters": [],
    "formats": []
  },
  "gameplay": {
    "Classic": {
      "mulligan": {
        "info": "",
        "startingHandSize": "6",
        "drawNewHand": true,
        "putSelectionAtBottom": false,
        "drawNewSelectedCards": false
      },
      "newTurn": {
        "drawOnStart": true,
        "sharedTurn": false,
        "firstPlayerTokenName": "",
        "drawPerTurn": "61"
      },
      "defaultNotes": "",
      "tokens": [],
      "countersStartingValues": [
        0
      ],
      "hideFacedDownCards": false,
      "sections": {
        "customSections": [
          "Front-Line",
          "Rear-Line"
        ],
        "layout": {
          "direction": "row",
          "isSymetricalForOpponents": false,
          "content": []
        },
        "categoriesAlreadyOnBoard": [
          "Minor/Major Arcana Deck",
          "Core Arcana Deck"
        ],
        "autoPlayFromHand": {},
        "autoPlayFromStack": {},
        "sectionsDict": {
          "Mana": {
            "title": "Mana",
            "isHidden": "no",
            "height": "SMALL",
            "alignment": "START",
            "opponentAlignment": false,
            "noAutoPayTo": "true",
            "isHorizontalAllowed": false,
            "displayedTitle": "Ressources",
            "enterTapped": false,
            "enterSpun": false,
            "isGroupForbidden": false,
            "keepTappedNewTurn": false,
            "showHiddenCardInHistory": false,
            "noQuickActions": false
          }
        }
      }
    }
  }
}
